json2markdown/__init__.py
json2markdown/core.py
json2markdown-0.1.1.dist-info/METADATA
json2markdown-0.1.1.dist-info/WHEEL
json2markdown-0.1.1.dist-info/top_level.txt
json2markdown-0.1.1.dist-info/RECORD
